oocprocess/__init__.py
oocprocess/preprocess.py
oocprocess-0.2.3.dist-info/LICENSE
oocprocess-0.2.3.dist-info/METADATA
oocprocess-0.2.3.dist-info/WHEEL
oocprocess-0.2.3.dist-info/top_level.txt
oocprocess-0.2.3.dist-info/RECORD
